topsis_shivank/__init__.py
topsis_shivank/run_topsis.py
topsis_shivank_102303655-0.2.3.dist-info/licenses/LICENSE.txt
topsis_shivank_102303655-0.2.3.dist-info/METADATA
topsis_shivank_102303655-0.2.3.dist-info/WHEEL
topsis_shivank_102303655-0.2.3.dist-info/entry_points.txt
topsis_shivank_102303655-0.2.3.dist-info/top_level.txt
topsis_shivank_102303655-0.2.3.dist-info/RECORD
