Metadata-Version: 2.4
Name: topsis-shivank-102303655
Version: 0.2.3
Summary: Command line implementation of TOPSIS for MCDM problems
Author: Shivank Bhatia
Author-email: bhatiashivankwork@gmail.com
License: MIT
Requires-Python: >=3.8
License-File: LICENSE.txt
Requires-Dist: pandas
Dynamic: author
Dynamic: author-email
Dynamic: description
Dynamic: description-content-type
Dynamic: license
Dynamic: license-file
Dynamic: requires-dist
Dynamic: requires-python
Dynamic: summary
